Metadata-Version: 2.1
Name: CveattLib
Version: 0.0.1
Summary: Gaussian and Binomial distributions
Home-page: https://github.com/cveatt/demo
Author: cveatt
Author-email: Anastasiia.Belik@aug-global.com
